nicetable/__init__.py
nicetable/aux_functions.py
nicetable/examples.py
nicetable/nicetable.py
nicetable/test_nicetable.py
nicetable-0.7.0.dist-info/LICENSE
nicetable-0.7.0.dist-info/METADATA
nicetable-0.7.0.dist-info/WHEEL
nicetable-0.7.0.dist-info/top_level.txt
nicetable-0.7.0.dist-info/RECORD
