Metadata-Version: 2.1
Name: nicetable
Version: 0.7.0
Summary: A clean and elegant way to print text tables in Python with minimal boilerplate code
Home-page: https://github.com/ofirmanor/nicetable
Author: Ofir Manor
Author-email: ofir.manor@gmail.com
License: MIT
Keywords: table tabular textual display data formatter ascii
Platform: UNKNOWN
Classifier: Programming Language :: Python :: 3.6
Classifier: Programming Language :: Python :: 3.7
Classifier: License :: OSI Approved :: MIT License
Classifier: Operating System :: OS Independent
Classifier: Development Status :: 4 - Beta
Requires-Python: >=3.6
